roufcp/__init__.py
roufcp/roufcp.py
roufcp/tests/__init__.py
roufcp/tests/test_roufcp.py
roufcp-0.1.1.dist-info/LICENSE
roufcp-0.1.1.dist-info/METADATA
roufcp-0.1.1.dist-info/WHEEL
roufcp-0.1.1.dist-info/top_level.txt
roufcp-0.1.1.dist-info/RECORD
