Metadata-Version: 2.1
Name: roufcp
Version: 0.1.1
Summary: A python package for detecting gradual changepoint using Fuzzy Rough CP (roufCP)
Home-page: https://github.com/subroy13/roufcp
Author: Subhrajyoty Roy
Author-email: subhrajyotyroy@gmail.com
License: MIT
Platform: UNKNOWN
Classifier: Programming Language :: Python :: 3
Classifier: License :: OSI Approved :: MIT License
Classifier: Operating System :: OS Independent
Classifier: Intended Audience :: Science/Research
Classifier: Topic :: Scientific/Engineering
Requires-Python: >=3.0
Requires-Dist: numpy
Requires-Dist: scipy
Requires-Dist: statsmodels
